<plugins>
<pyqgis_plugin name="atlasprint" version="v3.2.2">
        <description>Add atlas capabilities for getPrint request in WMS for QGIS Server</description>
        <version>v3.2.2</version>
        <qgis_minimum_version>3.10</qgis_minimum_version>
        <homepage>https://github.com/3liz/qgis-atlasprint</homepage>
        <file_name>atlasprint.v3.2.2.zip</file_name>
        <icon>icon.png</icon>
        <author_name>3Liz</author_name>
        <download_url>https://github.com/3liz/qgis-atlasprint/releases/download/v3.2.2/atlasprint.v3.2.2.zip</download_url>
        <uploaded_by>Gustry</uploaded_by>
        <create_date>2021-04-29</create_date>
        <update_date>2021-04-29</update_date>
        <experimental>False</experimental>
        <deprecated>False</deprecated>
        <tracker>https://github.com/3liz/qgis-atlasprint/issues</tracker>
        <repository>https://github.com/3liz/qgis-atlasprint</repository>
        <tags>server,print,atlas</tags>
    </pyqgis_plugin>
<pyqgis_plugin name="wfsOutputExtension" version="v1.5.2">
        <description>Adds additional output formats to WFS GetFeature request on QGIS Server such as Geopackage, ODS, CSV etc</description>
        <version>v1.5.2</version>
        <qgis_minimum_version>3.0</qgis_minimum_version>
        <homepage>https://github.com/3liz/qgis-wfsOutputExtension</homepage>
        <file_name>wfsOutputExtension.v1.5.2.zip</file_name>
        <icon>icon.png</icon>
        <author_name>3Liz</author_name>
        <download_url>https://github.com/3liz/qgis-wfsOutputExtension/releases/download/v1.5.2/wfsOutputExtension.v1.5.2.zip</download_url>
        <uploaded_by>Gustry</uploaded_by>
        <create_date>2021-02-26</create_date>
        <update_date>2021-02-26</update_date>
        <experimental>True</experimental>
        <deprecated>False</deprecated>
        <tracker>https://github.com/3liz/qgis-wfsOutputExtension/issues</tracker>
        <repository>https://github.com/3liz/qgis-wfsOutputExtension</repository>
        <tags>server,format,wfs,ogc,lizmap,web,extension</tags>
    </pyqgis_plugin>
<pyqgis_plugin name="wfsOutputExtension" version="v1.5.3">
        <description>Adds additional output formats to WFS GetFeature request on QGIS Server such as Geopackage, ODS, CSV etc</description>
        <version>v1.5.3</version>
        <qgis_minimum_version>3.0</qgis_minimum_version>
        <homepage>https://github.com/3liz/qgis-wfsOutputExtension</homepage>
        <file_name>wfsOutputExtension.v1.5.3.zip</file_name>
        <icon>icon.png</icon>
        <author_name>3Liz</author_name>
        <download_url>https://github.com/3liz/qgis-wfsOutputExtension/releases/download/v1.5.3/wfsOutputExtension.v1.5.3.zip</download_url>
        <uploaded_by>Gustry</uploaded_by>
        <create_date>2021-05-05</create_date>
        <update_date>2021-05-05</update_date>
        <experimental>False</experimental>
        <deprecated>False</deprecated>
        <tracker>https://github.com/3liz/qgis-wfsOutputExtension/issues</tracker>
        <repository>https://github.com/3liz/qgis-wfsOutputExtension</repository>
        <tags>server,format,wfs,ogc,lizmap,web,extension</tags>
    </pyqgis_plugin>
<pyqgis_plugin name="Drain sewer visual inspection" version="0.2.0">
        <description>Drain and sewer systems visual inspection coding system (EN 13508-2)</description>
        <version>0.2.0</version>
        <qgis_minimum_version>3.4</qgis_minimum_version>
        <homepage>https://github.com/3liz/qgis_drain_sewer_visual_inspection</homepage>
        <file_name>drain_sewer_visual_inspection.0.2.0.zip</file_name>
        <icon>resources/icons/icon.png</icon>
        <author_name>3liz</author_name>
        <download_url>https://github.com/3liz/qgis_drain_sewer_visual_inspection/releases/download/0.2.0/drain_sewer_visual_inspection.0.2.0.zip</download_url>
        <uploaded_by>3liz</uploaded_by>
        <create_date>2021-05-07</create_date>
        <update_date>2021-05-07</update_date>
        <experimental>False</experimental>
        <deprecated>False</deprecated>
        <tracker>https://github.com/3liz/qgis_drain_sewer_visual_inspection/issues</tracker>
        <repository>https://github.com/3liz/qgis_drain_sewer_visual_inspection</repository>
        <tags>drain,sewer,pipe,pipeline,inspection,EN13508,water,hydraulic,pvi</tags>
    </pyqgis_plugin>
<pyqgis_plugin name="PgMetadata" version="1.0.0">
        <description>Store some metadata about layers which are stored in PostgreSQL. It's possible to define title, abstract, links, contacts etc. It also provides some search tool, in the QGIS Locator bar for instance.</description>
        <version>1.0.0</version>
        <qgis_minimum_version>3.10</qgis_minimum_version>
        <homepage>https://docs.3liz.org/qgis-pgmetadata-plugin/</homepage>
        <file_name>pg_metadata.1.0.0.zip</file_name>
        <icon>resources/icons/icon.png</icon>
        <author_name>3Liz</author_name>
        <download_url>https://github.com/3liz/qgis-pgmetadata-plugin/releases/download/1.0.0/pg_metadata.1.0.0.zip</download_url>
        <uploaded_by>Gustry</uploaded_by>
        <create_date>2021-05-27</create_date>
        <update_date>2021-05-27</update_date>
        <experimental>False</experimental>
        <deprecated>False</deprecated>
        <tracker>https://github.com/3liz/qgis-pgmetadata-plugin/issues</tracker>
        <repository>https://github.com/3liz/qgis-pgmetadata-plugin</repository>
        <tags>metadata,postgresql,qgis,metadonnees,dcat,xml,csv</tags>
    </pyqgis_plugin>
<pyqgis_plugin name="QuickOSM" version="1.17.1">
        <description>Download OSM data thanks to the Overpass API. You can also open local OSM or PBF files. A special parser, on top of OGR, is used to let you see all OSM keys available.</description>
        <version>1.17.1</version>
        <qgis_minimum_version>3.4</qgis_minimum_version>
        <homepage>https://docs.3liz.org/QuickOSM/</homepage>
        <file_name>QuickOSM.1.17.1.zip</file_name>
        <icon>resources/icons/QuickOSM.svg</icon>
        <author_name>Etienne Trimaille</author_name>
        <download_url>https://github.com/3liz/QuickOSM/releases/download/1.17.1/QuickOSM.1.17.1.zip</download_url>
        <uploaded_by>Gustry</uploaded_by>
        <create_date>2021-06-24</create_date>
        <update_date>2021-06-24</update_date>
        <experimental>False</experimental>
        <deprecated>False</deprecated>
        <tracker>https://github.com/3liz/QuickOSM/issues</tracker>
        <repository>https://github.com/3liz/QuickOSM</repository>
        <tags>osm,openstreetmap,overpass,download,osmdownload,josm,remote,pbf,processing,modeler</tags>
    </pyqgis_plugin>
<pyqgis_plugin name="V&#233;loroutes Voies Vertes" version="1.0.0">
        <description>French use-case only for cycling routes following the COVADIS Standard. Extension pour la gestion des v&#233;louroutes et voies vertes selon le standard COVADIS</description>
        <version>1.0.0</version>
        <qgis_minimum_version>3.10</qgis_minimum_version>
        <homepage>https://github.com/3liz/qgis-veloroutes_voies_vertes-plugin</homepage>
        <file_name>veloroutes_voies_vertes.1.0.0.zip</file_name>
        <icon>resources/icons/icon.png</icon>
        <author_name>3Liz</author_name>
        <download_url>https://github.com/3liz/qgis-veloroutes_voies_vertes-plugin/releases/download/1.0.0/veloroutes_voies_vertes.1.0.0.zip</download_url>
        <uploaded_by>Gustry</uploaded_by>
        <create_date>2021-07-01</create_date>
        <update_date>2021-07-01</update_date>
        <experimental>False</experimental>
        <deprecated>False</deprecated>
        <tracker>https://github.com/3liz/qgis-veloroutes_voies_vertes-plugin</tracker>
        <repository>https://github.com/3liz/qgis-veloroutes_voies_vertes-plugin</repository>
        <tags>covadis,veloroutes,velo,voies vertes</tags>
    </pyqgis_plugin>
<pyqgis_plugin name="Mercicor" version="1.0.2">
        <description>Methodology for Scaling Mitigation and Compensatory Measures in Tropical Marine Ecosystems. The plugin is available in French only for now.; M&#233;thode biophysiques d&#8217;&#233;valuation des effets de l&#8217;am&#233;nagement sur l&#8217;environnement marin tropical. L'extension est disponible en Fran&#231;ais seulement.</description>
        <version>1.0.2</version>
        <qgis_minimum_version>3.10</qgis_minimum_version>
        <homepage>https://docs.3liz.org/qgis-mercicor-plugin/</homepage>
        <file_name>mercicor.1.0.2.zip</file_name>
        <icon>resources/icons/icon.png</icon>
        <author_name>3Liz</author_name>
        <download_url>https://github.com/3liz/qgis-mercicor-plugin/releases/download/1.0.2/mercicor.1.0.2.zip</download_url>
        <uploaded_by>Gustry</uploaded_by>
        <create_date>2021-07-06</create_date>
        <update_date>2021-07-06</update_date>
        <experimental>False</experimental>
        <deprecated>False</deprecated>
        <tracker>https://github.com/3liz/qgis-mercicor-plugin/issues</tracker>
        <repository>https://github.com/3liz/qgis-mercicor-plugin</repository>
        <tags>mercicor</tags>
    </pyqgis_plugin>
<pyqgis_plugin name="Lizmap" version="3.5.5">
        <description>Publish and share your QGIS maps on the Web via Lizmap Web Client, by 3liz.com</description>
        <version>3.5.5</version>
        <qgis_minimum_version>3.4</qgis_minimum_version>
        <homepage>https://docs.lizmap.com</homepage>
        <file_name>lizmap.3.5.5.zip</file_name>
        <icon>resources/icons/icon.png</icon>
        <author_name>3Liz</author_name>
        <download_url>https://github.com/3liz/lizmap-plugin/releases/download/3.5.5/lizmap.3.5.5.zip</download_url>
        <uploaded_by>Gustry</uploaded_by>
        <create_date>2021-08-09</create_date>
        <update_date>2021-08-09</update_date>
        <experimental>False</experimental>
        <deprecated>False</deprecated>
        <tracker>https://github.com/3liz/lizmap-plugin/issues</tracker>
        <repository>https://github.com/3liz/lizmap-plugin</repository>
        <tags>online,server,web,webgis,webservice,webmapping,mobile,publication,wms,wfs,wps,internet,cloud,dashboard</tags>
    </pyqgis_plugin>
<pyqgis_plugin name="cadastre" version="1.13.1">
        <description>This plugins helps users to use French land registry data, called Cadastre, in QGIS. It is only useful in</description>
        <version>1.13.1</version>
        <qgis_minimum_version>3.4</qgis_minimum_version>
        <homepage>https://docs.3liz.org/QgisCadastrePlugin/</homepage>
        <file_name>cadastre.1.13.1.zip</file_name>
        <icon>icon.png</icon>
        <author_name>3Liz</author_name>
        <download_url>https://github.com/3liz/QgisCadastrePlugin/releases/download/1.13.1/cadastre.1.13.1.zip</download_url>
        <uploaded_by>Gustry</uploaded_by>
        <create_date>2021-08-10</create_date>
        <update_date>2021-08-10</update_date>
        <experimental>False</experimental>
        <deprecated>False</deprecated>
        <tracker>https://github.com/3liz/QgisCadastrePlugin/issues</tracker>
        <repository>https://github.com/3liz/QgisCadastrePlugin</repository>
        <tags>cadastre, france, majic, edigeo, import</tags>
    </pyqgis_plugin>
</plugins>